client.py
termux_openai-1.0.0.dist-info/METADATA
termux_openai-1.0.0.dist-info/WHEEL
termux_openai-1.0.0.dist-info/top_level.txt
termux_openai-1.0.0.dist-info/RECORD
